{
    "https://chase.com": {
        "data": {
            "0": {
                "link-0": {
                    "WORDS": {
                        "we": {
                            "text": {
                                "we": [
                                    {
                                        "0": "We and our partners use cookies and other tools for advertising, to help stop fraud, and for other purposes. By using this site, you agree to how your information is used as outlined in our Privacy Policy."
                                    },
                                    {
                                        "1": "How we protect you"
                                    },
                                    {
                                        "2": "How we protect you"
                                    },
                                    {
                                        "3": "How we protect you"
                                    },
                                    {
                                        "4": "We're continuously working to make your banking safer. See how we're dedicated to helping protect you and your accounts."
                                    },
                                    {
                                        "5": "How we protect you"
                                    },
                                    {
                                        "6": "We're continuously working to make your banking safer. See how we're dedicated to helping protect you and your accounts."
                                    },
                                    {
                                        "7": "We value your privacy"
                                    },
                                    {
                                        "8": "We treat your personal and financial information with care. Our Privacy Policy explains how."
                                    },
                                    {
                                        "9": "\"We've detected malware on your computer. Let's get that fixed for you. There will be a small cost to make your computer secure.\""
                                    },
                                    {
                                        "10": "How we help protect you"
                                    },
                                    {
                                        "11": "We're working to make your banking safer. See how we're helping to protect you and your accounts.\n"
                                    },
                                    {
                                        "12": ",   on how we work to protect you"
                                    },
                                    {
                                        "13": "If it's a phone call, hang up. If it's an email or text message, stop responding. If you think you've given the scammer personal or account information, please contact us so we can help assess your situation."
                                    },
                                    {
                                        "14": "If you see that money was removed from your checking or savings accounts through our mobile or online banking bill pay or transfer services and you didn’t authorize the transaction, let us know right away. We’ll reimburse you for those unauthorized transactions when you contact us promptly after the transaction first appears on your statement."
                                    },
                                    {
                                        "15": "Our suite of security features can help you protect your info, money and give you peace of mind. See how we're dedicated to helping protect you, your accounts and your loved ones from financial abuse. Also, learn about the common tricks scammers are using to help you stay one step ahead of them. If you see unauthorized charges or believe your account was compromised contact us right away to report fraud."
                                    }
                                ]
                            },
                            "count": 16
                        },
                        "promise": {
                            "text": {},
                            "count": 0
                        },
                        "only": {
                            "text": {},
                            "count": 0
                        },
                        "information": {
                            "text": {
                                "information": [
                                    {
                                        "0": "We and our partners use cookies and other tools for advertising, to help stop fraud, and for other purposes. By using this site, you agree to how your information is used as outlined in our Privacy Policy."
                                    },
                                    {
                                        "1": "We treat your personal and financial information with care. Our Privacy Policy explains how."
                                    },
                                    {
                                        "2": "Many of us rely on technology to store and access financial information. Learn about the online do's and don'ts to help stay protected.\n"
                                    },
                                    {
                                        "3": "If it's a phone call, hang up. If it's an email or text message, stop responding. If you think you've given the scammer personal or account information, please contact us so we can help assess your situation."
                                    },
                                    {
                                        "4": "Zelle® is intended for payments to recipients you know and trust and is not intended for the purchase of goods from retailers, online marketplaces or through social media posts. Neither Zelle® nor Chase provide protection if you make a purchase of goods using Zelle® and then do not receive them or receive them damaged or not as described or expected. In case of errors or questions about your electronic funds transfers, including information on reimbursement for fraudulent Zelle® payments, see your account agreement. Neither Chase nor Zelle® offers reimbursement for authorized payments you make using Zelle®, except for a limited reimbursement program that applies for certain imposter scams where you sent money with Zelle®. This reimbursement program is not required by law and may be modified or discontinued at any time."
                                    },
                                    {
                                        "5": "Chase serves millions of people with a broad range of products. Chase online lets you manage your Chase accounts, view statements, monitor activity, pay bills or transfer funds securely from one central place. To learn more, visit the Banking Education Center. For questions or concerns, please contact Chase customer service or let us know about Chase complaints and feedback. View the Chase Community Reinvestment Act Public File for the bank’s latest CRA rating and other CRA-related information."
                                    }
                                ]
                            },
                            "count": 6
                        },
                        "use": {
                            "text": {
                                "use": [
                                    {
                                        "0": "We and our partners use cookies and other tools for advertising, to help stop fraud, and for other purposes. By using this site, you agree to how your information is used as outlined in our Privacy Policy."
                                    },
                                    {
                                        "1": "How to use Zelle® safely"
                                    },
                                    {
                                        "2": "How to use Zelle® safely"
                                    },
                                    {
                                        "3": "Learn how to help take control of your future by recognizing the signs of financial abuse and exploitation. Get the tools to help you stay safe."
                                    },
                                    {
                                        "4": "Recognize the signs of financial abuse and exploitation. Get the tools you need to help you stay safe.\n"
                                    },
                                    {
                                        "5": "Enrollment in Zelle® with a U.S. checking or savings account is required to use the service. Chase customers must use an eligible Chase consumer or business checking account, which may have its own account fees. Consult your account agreement. To send money to or receive money from a small business, both parties must be enrolled with Zelle® directly through their financial institution’s online or mobile app experience. Funds are typically made available in minutes when the recipient’s email address or U.S. mobile number is already enrolled with Zelle® (go to enroll.zellepay.com , Opens overlayto view participating banks). Select transactions could take up to 3 business days. Enroll on the Chase Mobile® app or Chase Online℠. Limitations may apply. Message and data rates may apply."
                                    },
                                    {
                                        "6": "Zero Liability: Zero Liability Protection does not apply to use of an account by an authorized user without the approval of the primary cardmember. If you think someone used your account without permission, tell us immediately by calling the Cardmember Services number on your card or billing statement."
                                    },
                                    {
                                        "7": "Chase Auto is here to help you get the right car. Apply for auto financing for a new or used car with Chase. Use the payment calculator to estimate monthly payments. Check out the Chase Auto Education Center to get car guidance from a trusted source."
                                    },
                                    {
                                        "8": "Our suite of security features can help you protect your info, money and give you peace of mind. See how we're dedicated to helping protect you, your accounts and your loved ones from financial abuse. Also, learn about the common tricks scammers are using to help you stay one step ahead of them. If you see unauthorized charges or believe your account was compromised contact us right away to report fraud."
                                    }
                                ]
                            },
                            "count": 9
                        },
                        "why": {
                            "text": {},
                            "count": 0
                        },
                        "priv": {
                            "text": {},
                            "count": 0
                        },
                        "other": {
                            "text": {
                                "other": [
                                    {
                                        "0": "We and our partners use cookies and other tools for advertising, to help stop fraud, and for other purposes. By using this site, you agree to how your information is used as outlined in our Privacy Policy."
                                    },
                                    {
                                        "1": "Scam emails are often poorly written. Look out for typos, grammatical errors and other signs that an email was not written by a legitimate company."
                                    },
                                    {
                                        "2": "Chase serves millions of people with a broad range of products. Chase online lets you manage your Chase accounts, view statements, monitor activity, pay bills or transfer funds securely from one central place. To learn more, visit the Banking Education Center. For questions or concerns, please contact Chase customer service or let us know about Chase complaints and feedback. View the Chase Community Reinvestment Act Public File for the bank’s latest CRA rating and other CRA-related information."
                                    },
                                    {
                                        "3": "NOT A DEPOSIT OR OTHER OBLIGATION OF, OR GUARANTEED BY, JPMORGAN CHASE BANK, N.A. OR ANY OF ITS AFFILIATES"
                                    },
                                    {
                                        "4": "Other Products & Services:"
                                    },
                                    {
                                        "5": "Other products"
                                    }
                                ]
                            },
                            "count": 6
                        },
                        "if": {
                            "text": {
                                "if": [
                                    {
                                        "0": "How do I know if an email received is a scam?"
                                    },
                                    {
                                        "1": "What should I do if I suspect I've been targeted by a scammer?"
                                    },
                                    {
                                        "2": "If it's a phone call, hang up. If it's an email or text message, stop responding. If you think you've given the scammer personal or account information, please contact us so we can help assess your situation."
                                    },
                                    {
                                        "3": "You won't be held responsible for unauthorized charges made with your credit card. If you see an unauthorized charge, tell us immediately by calling the number on the back of your card or billing statement\n        \n        Footnote\n        2Opens overlay."
                                    },
                                    {
                                        "4": "If you see that money was removed from your checking or savings accounts through our mobile or online banking bill pay or transfer services and you didn’t authorize the transaction, let us know right away. We’ll reimburse you for those unauthorized transactions when you contact us promptly after the transaction first appears on your statement."
                                    },
                                    {
                                        "5": "Zelle® is intended for payments to recipients you know and trust and is not intended for the purchase of goods from retailers, online marketplaces or through social media posts. Neither Zelle® nor Chase provide protection if you make a purchase of goods using Zelle® and then do not receive them or receive them damaged or not as described or expected. In case of errors or questions about your electronic funds transfers, including information on reimbursement for fraudulent Zelle® payments, see your account agreement. Neither Chase nor Zelle® offers reimbursement for authorized payments you make using Zelle®, except for a limited reimbursement program that applies for certain imposter scams where you sent money with Zelle®. This reimbursement program is not required by law and may be modified or discontinued at any time."
                                    },
                                    {
                                        "6": "Zero Liability: Zero Liability Protection does not apply to use of an account by an authorized user without the approval of the primary cardmember. If you think someone used your account without permission, tell us immediately by calling the Cardmember Services number on your card or billing statement."
                                    },
                                    {
                                        "7": "Our suite of security features can help you protect your info, money and give you peace of mind. See how we're dedicated to helping protect you, your accounts and your loved ones from financial abuse. Also, learn about the common tricks scammers are using to help you stay one step ahead of them. If you see unauthorized charges or believe your account was compromised contact us right away to report fraud."
                                    }
                                ]
                            },
                            "count": 8
                        },
                        "when": {
                            "text": {
                                "when": [
                                    {
                                        "0": "Learn how to steer clear of scammers when using Zelle®"
                                    },
                                    {
                                        "1": "If you see that money was removed from your checking or savings accounts through our mobile or online banking bill pay or transfer services and you didn’t authorize the transaction, let us know right away. We’ll reimburse you for those unauthorized transactions when you contact us promptly after the transaction first appears on your statement."
                                    },
                                    {
                                        "2": "Enrollment in Zelle® with a U.S. checking or savings account is required to use the service. Chase customers must use an eligible Chase consumer or business checking account, which may have its own account fees. Consult your account agreement. To send money to or receive money from a small business, both parties must be enrolled with Zelle® directly through their financial institution’s online or mobile app experience. Funds are typically made available in minutes when the recipient’s email address or U.S. mobile number is already enrolled with Zelle® (go to enroll.zellepay.com , Opens overlayto view participating banks). Select transactions could take up to 3 business days. Enroll on the Chase Mobile® app or Chase Online℠. Limitations may apply. Message and data rates may apply."
                                    }
                                ]
                            },
                            "count": 3
                        },
                        "help": {
                            "text": {
                                "help": [
                                    {
                                        "0": "We and our partners use cookies and other tools for advertising, to help stop fraud, and for other purposes. By using this site, you agree to how your information is used as outlined in our Privacy Policy."
                                    },
                                    {
                                        "1": "See help options"
                                    },
                                    {
                                        "2": "Our suite of security features can help protect your info and money, and give you peace of mind."
                                    },
                                    {
                                        "3": "Help safeguard seniors"
                                    },
                                    {
                                        "4": "Help safeguard seniors"
                                    },
                                    {
                                        "5": "Let's work together to help keep your account safe"
                                    },
                                    {
                                        "6": "Add extra protection to your account to help keep yourself safe from fraud and scams."
                                    },
                                    {
                                        "7": "Add extra protection to your account to help keep yourself safe from fraud and scams."
                                    },
                                    {
                                        "8": "Older adults in particular are at risk for fraud. Learn how you can help us protect your accounts."
                                    },
                                    {
                                        "9": "Learn how to help take control of your future by recognizing the signs of financial abuse and exploitation. Get the tools to help you stay safe."
                                    },
                                    {
                                        "10": "Learn more about the common tricks scammers are using to help keep yourself safe."
                                    },
                                    {
                                        "11": " Let's work together to help protect you and those you love"
                                    },
                                    {
                                        "12": "How we help protect you"
                                    },
                                    {
                                        "13": "What you can do to help protect yourself"
                                    },
                                    {
                                        "14": "Learn safety practices and the steps you can take to help protect yourself from fraud and scams.\n"
                                    },
                                    {
                                        "15": "Help protect your money as you age"
                                    },
                                    {
                                        "16": "Recognize the signs of financial abuse and exploitation. Get the tools you need to help you stay safe.\n"
                                    },
                                    {
                                        "17": "Scammers spend their days coming up with new ways to trick us. Learn what to watch out for to help keep yourself safe.\n"
                                    },
                                    {
                                        "18": "Help guard yourself against online threats"
                                    },
                                    {
                                        "19": "Many of us rely on technology to store and access financial information. Learn about the online do's and don'ts to help stay protected.\n"
                                    },
                                    {
                                        "20": "If it's a phone call, hang up. If it's an email or text message, stop responding. If you think you've given the scammer personal or account information, please contact us so we can help assess your situation."
                                    },
                                    {
                                        "21": "Chase credit cards can help you buy the things you need. Many of our cards offer rewards that can be redeemed for cash back or travel-related perks. With so many options, it can be easy to find a card that matches your lifestyle. Plus, with Credit Journey you can get a free credit score!"
                                    },
                                    {
                                        "22": "Chase Auto is here to help you get the right car. Apply for auto financing for a new or used car with Chase. Use the payment calculator to estimate monthly payments. Check out the Chase Auto Education Center to get car guidance from a trusted source."
                                    },
                                    {
                                        "23": "help you protect"
                                    },
                                    {
                                        "24": "Whether you choose to work with a financial advisor and develop a financial strategy or invest online, J.P. Morgan offers investment education, expertise and a range of tools to help you reach your goals. Visit a J.P. Morgan Wealth Management Branch or check out our latest online investing offers, promotions, and coupons."
                                    }
                                ]
                            },
                            "count": 25
                        },
                        "access": {
                            "text": {
                                "access": [
                                    {
                                        "0": "Access calculators and tools"
                                    },
                                    {
                                        "1": "TIP: Never give anyone remote access to your computer unless you can 100% verify who they are."
                                    },
                                    {
                                        "2": "Many of us rely on technology to store and access financial information. Learn about the online do's and don'ts to help stay protected.\n"
                                    },
                                    {
                                        "3": "Chase gives you access to unique sports, entertainment and culinary events through Chase Experiences and our exclusive partnerships such as the US Open, Madison Square Garden, Opens overlay and Chase Center."
                                    }
                                ]
                            },
                            "count": 4
                        },
                        "can't access": {
                            "text": {},
                            "count": 0
                        }
                    },
                    "CAPABILITY": {
                        "we will not": {
                            "text": {},
                            "count": 0
                        },
                        "we only": {
                            "text": {},
                            "count": 0
                        },
                        "we collect": {
                            "text": {},
                            "count": 0
                        },
                        "we may collect": {
                            "text": {},
                            "count": 0
                        },
                        "we gather data": {
                            "text": {},
                            "count": 0
                        },
                        "you may": {
                            "text": {
                                "you may": [
                                    {
                                        "0": "TIP: Be cautious of great \"deals\" on social media sites. Once you send money you may not get it back."
                                    },
                                    {
                                        "1": "Think you may have experienced fraud? Here's what to do next."
                                    },
                                    {
                                        "2": "You may also want to report suspicious calls, emails, and text messages to the U.S. Federal Trade Commission, Opens overlay."
                                    }
                                ]
                            },
                            "count": 3
                        },
                        "you can": {
                            "text": {
                                "you can": [
                                    {
                                        "0": "What you can do"
                                    },
                                    {
                                        "1": "What you can do"
                                    },
                                    {
                                        "2": "What you can do"
                                    },
                                    {
                                        "3": ",   on what you can do to protect yourself"
                                    },
                                    {
                                        "4": "What you can do"
                                    },
                                    {
                                        "5": ",   on what you can do to protect yourself"
                                    },
                                    {
                                        "6": "Zelle® is a fast and convenient way to send and receive money with people you know and trust like friends and family. But using it to send money to someone you don’t know, or to pay for merchandise or services you can’t be sure you’ll get, can be risky."
                                    },
                                    {
                                        "7": "Older adults in particular are at risk for fraud. Learn how you can help us protect your accounts."
                                    },
                                    {
                                        "8": "\"Get a great price on these exclusive sneakers. You can pay using cash or a payment app.\""
                                    },
                                    {
                                        "9": "TIP: Never give anyone remote access to your computer unless you can 100% verify who they are."
                                    },
                                    {
                                        "10": "What you can do to help protect yourself"
                                    },
                                    {
                                        "11": "Learn safety practices and the steps you can take to help protect yourself from fraud and scams.\n"
                                    },
                                    {
                                        "12": "Chase credit cards can help you buy the things you need. Many of our cards offer rewards that can be redeemed for cash back or travel-related perks. With so many options, it can be easy to find a card that matches your lifestyle. Plus, with Credit Journey you can get a free credit score!"
                                    },
                                    {
                                        "13": "Apply for a mortgage or refinance your mortgage with Chase. View today’s mortgage rates or calculate what you can afford with our mortgage calculator. Visit our Education Center for homebuying tips and more."
                                    }
                                ]
                            },
                            "count": 14
                        },
                        "right": {
                            "text": {
                                "right": [
                                    {
                                        "0": "If you see that money was removed from your checking or savings accounts through our mobile or online banking bill pay or transfer services and you didn’t authorize the transaction, let us know right away. We’ll reimburse you for those unauthorized transactions when you contact us promptly after the transaction first appears on your statement."
                                    },
                                    {
                                        "1": "Chase Auto is here to help you get the right car. Apply for auto financing for a new or used car with Chase. Use the payment calculator to estimate monthly payments. Check out the Chase Auto Education Center to get car guidance from a trusted source."
                                    },
                                    {
                                        "2": "Our suite of security features can help you protect your info, money and give you peace of mind. See how we're dedicated to helping protect you, your accounts and your loved ones from financial abuse. Also, learn about the common tricks scammers are using to help you stay one step ahead of them. If you see unauthorized charges or believe your account was compromised contact us right away to report fraud."
                                    }
                                ]
                            },
                            "count": 3
                        },
                        "choice": {
                            "text": {},
                            "count": 0
                        },
                        "request": {
                            "text": {},
                            "count": 0
                        },
                        "delete": {
                            "text": {},
                            "count": 0
                        },
                        "deletion": {
                            "text": {},
                            "count": 0
                        },
                        "remove": {
                            "text": {},
                            "count": 0
                        },
                        "removal": {
                            "text": {},
                            "count": 0
                        },
                        "erase": {
                            "text": {},
                            "count": 0
                        }
                    },
                    "LEGAL": {
                        "contract": {
                            "text": {},
                            "count": 0
                        },
                        "agreement": {
                            "text": {
                                "agreement": [
                                    {
                                        "0": "Deposit Agreement (PDF)"
                                    },
                                    {
                                        "1": "Digital Services Agreement (PDF)"
                                    },
                                    {
                                        "2": "Enrollment in Zelle® with a U.S. checking or savings account is required to use the service. Chase customers must use an eligible Chase consumer or business checking account, which may have its own account fees. Consult your account agreement. To send money to or receive money from a small business, both parties must be enrolled with Zelle® directly through their financial institution’s online or mobile app experience. Funds are typically made available in minutes when the recipient’s email address or U.S. mobile number is already enrolled with Zelle® (go to enroll.zellepay.com , Opens overlayto view participating banks). Select transactions could take up to 3 business days. Enroll on the Chase Mobile® app or Chase Online℠. Limitations may apply. Message and data rates may apply."
                                    },
                                    {
                                        "3": "Zelle® is intended for payments to recipients you know and trust and is not intended for the purchase of goods from retailers, online marketplaces or through social media posts. Neither Zelle® nor Chase provide protection if you make a purchase of goods using Zelle® and then do not receive them or receive them damaged or not as described or expected. In case of errors or questions about your electronic funds transfers, including information on reimbursement for fraudulent Zelle® payments, see your account agreement. Neither Chase nor Zelle® offers reimbursement for authorized payments you make using Zelle®, except for a limited reimbursement program that applies for certain imposter scams where you sent money with Zelle®. This reimbursement program is not required by law and may be modified or discontinued at any time."
                                    }
                                ]
                            },
                            "count": 4
                        },
                        "obligation": {
                            "text": {
                                "obligation": [
                                    {
                                        "0": "NOT A DEPOSIT OR OTHER OBLIGATION OF, OR GUARANTEED BY, JPMORGAN CHASE BANK, N.A. OR ANY OF ITS AFFILIATES"
                                    }
                                ]
                            },
                            "count": 1
                        },
                        "you control": {
                            "text": {},
                            "count": 0
                        },
                        "we control": {
                            "text": {},
                            "count": 0
                        },
                        "legal": {
                            "text": {},
                            "count": 0
                        },
                        "authority": {
                            "text": {},
                            "count": 0
                        },
                        "comply": {
                            "text": {},
                            "count": 0
                        },
                        "compliant": {
                            "text": {},
                            "count": 0
                        },
                        "law": {
                            "text": {
                                "law": [
                                    {
                                        "0": "Zelle® is intended for payments to recipients you know and trust and is not intended for the purchase of goods from retailers, online marketplaces or through social media posts. Neither Zelle® nor Chase provide protection if you make a purchase of goods using Zelle® and then do not receive them or receive them damaged or not as described or expected. In case of errors or questions about your electronic funds transfers, including information on reimbursement for fraudulent Zelle® payments, see your account agreement. Neither Chase nor Zelle® offers reimbursement for authorized payments you make using Zelle®, except for a limited reimbursement program that applies for certain imposter scams where you sent money with Zelle®. This reimbursement program is not required by law and may be modified or discontinued at any time."
                                    }
                                ]
                            },
                            "count": 1
                        },
                        "enforce": {
                            "text": {},
                            "count": 0
                        },
                        "govern": {
                            "text": {},
                            "count": 0
                        },
                        "regulators": {
                            "text": {},
                            "count": 0
                        },
                        "regulatory": {
                            "text": {},
                            "count": 0
                        },
                        "policy": {
                            "text": {
                                "policy": [
                                    {
                                        "0": "We and our partners use cookies and other tools for advertising, to help stop fraud, and for other purposes. By using this site, you agree to how your information is used as outlined in our Privacy Policy."
                                    },
                                    {
                                        "1": "We treat your personal and financial information with care. Our Privacy Policy explains how."
                                    },
                                    {
                                        "2": "\nOnline Privacy Policy\nU.S. Consumer Privacy Notice\nCCPA Disclosure\n"
                                    }
                                ]
                            },
                            "count": 3
                        },
                        "international": {
                            "text": {},
                            "count": 0
                        },
                        "in accordane with": {
                            "text": {},
                            "count": 0
                        },
                        "california": {
                            "text": {},
                            "count": 0
                        },
                        "children": {
                            "text": {},
                            "count": 0
                        },
                        "kid": {
                            "text": {},
                            "count": 0
                        },
                        "child": {
                            "text": {},
                            "count": 0
                        },
                        "youth": {
                            "text": {},
                            "count": 0
                        },
                        "young": {
                            "text": {},
                            "count": 0
                        },
                        "minor": {
                            "text": {},
                            "count": 0
                        },
                        "you consented": {
                            "text": {},
                            "count": 0
                        },
                        "you consent": {
                            "text": {},
                            "count": 0
                        },
                        "you agree": {
                            "text": {
                                "you agree": [
                                    {
                                        "0": "We and our partners use cookies and other tools for advertising, to help stop fraud, and for other purposes. By using this site, you agree to how your information is used as outlined in our Privacy Policy."
                                    }
                                ]
                            },
                            "count": 1
                        },
                        "your agreement": {
                            "text": {},
                            "count": 0
                        },
                        "you acknowledge": {
                            "text": {},
                            "count": 0
                        },
                        "you acknowledged": {
                            "text": {},
                            "count": 0
                        },
                        "you signed": {
                            "text": {},
                            "count": 0
                        },
                        "you approve": {
                            "text": {},
                            "count": 0
                        },
                        "you approved": {
                            "text": {},
                            "count": 0
                        },
                        "your permission": {
                            "text": {},
                            "count": 0
                        },
                        "you accepted": {
                            "text": {},
                            "count": 0
                        },
                        "you read": {
                            "text": {},
                            "count": 0
                        }
                    },
                    "BUSINESS_FOCUS": {
                        "third parties": {
                            "text": {},
                            "count": 0
                        },
                        "third-party": {
                            "text": {},
                            "count": 0
                        },
                        "third party": {
                            "text": {},
                            "count": 0
                        },
                        "advertising": {
                            "text": {
                                "advertising": [
                                    {
                                        "0": "We and our partners use cookies and other tools for advertising, to help stop fraud, and for other purposes. By using this site, you agree to how your information is used as outlined in our Privacy Policy."
                                    }
                                ]
                            },
                            "count": 1
                        },
                        "sends to": {
                            "text": {},
                            "count": 0
                        },
                        "sell to": {
                            "text": {},
                            "count": 0
                        },
                        "share with": {
                            "text": {},
                            "count": 0
                        },
                        "exchange": {
                            "text": {},
                            "count": 0
                        },
                        "improve": {
                            "text": {
                                "improve": [
                                    {
                                        "0": "With Chase for Business you’ll receive guidance from a team of business professionals who specialize in helping improve cash flow, providing credit solutions, and managing payroll. Choose from business checking, business credit cards, merchant services or visit our business resource center."
                                    }
                                ]
                            },
                            "count": 1
                        },
                        "optimize": {
                            "text": {},
                            "count": 0
                        },
                        "increase": {
                            "text": {},
                            "count": 0
                        },
                        "benefit": {
                            "text": {},
                            "count": 0
                        },
                        "enhance": {
                            "text": {},
                            "count": 0
                        },
                        "innovate": {
                            "text": {},
                            "count": 0
                        },
                        "technologial innovation": {
                            "text": {},
                            "count": 0
                        }
                    },
                    "UTILIZATION": {
                        "data": {
                            "text": {
                                "data": [
                                    {
                                        "0": "Enrollment in Zelle® with a U.S. checking or savings account is required to use the service. Chase customers must use an eligible Chase consumer or business checking account, which may have its own account fees. Consult your account agreement. To send money to or receive money from a small business, both parties must be enrolled with Zelle® directly through their financial institution’s online or mobile app experience. Funds are typically made available in minutes when the recipient’s email address or U.S. mobile number is already enrolled with Zelle® (go to enroll.zellepay.com , Opens overlayto view participating banks). Select transactions could take up to 3 business days. Enroll on the Chase Mobile® app or Chase Online℠. Limitations may apply. Message and data rates may apply."
                                    }
                                ]
                            },
                            "count": 1
                        },
                        "we process": {
                            "text": {},
                            "count": 0
                        },
                        "collected": {
                            "text": {},
                            "count": 0
                        },
                        "stored": {
                            "text": {},
                            "count": 0
                        },
                        "retention": {
                            "text": {},
                            "count": 0
                        }
                    },
                    "INNOVATION": {
                        "analyze": {
                            "text": {},
                            "count": 0
                        },
                        "analysis": {
                            "text": {},
                            "count": 0
                        },
                        "analytics": {
                            "text": {},
                            "count": 0
                        },
                        "automate": {
                            "text": {},
                            "count": 0
                        },
                        "automatic": {
                            "text": {},
                            "count": 0
                        },
                        "AI": {
                            "text": {},
                            "count": 0
                        },
                        "automatically": {
                            "text": {},
                            "count": 0
                        },
                        "artificial intelligence": {
                            "text": {},
                            "count": 0
                        },
                        "algorithm": {
                            "text": {},
                            "count": 0
                        },
                        "language processing": {
                            "text": {},
                            "count": 0
                        }
                    },
                    "SECURITY": {
                        "control": {
                            "text": {
                                "control": [
                                    {
                                        "0": "Learn how to help take control of your future by recognizing the signs of financial abuse and exploitation. Get the tools to help you stay safe."
                                    }
                                ]
                            },
                            "count": 1
                        },
                        "settings": {
                            "text": {},
                            "count": 0
                        },
                        "controls": {
                            "text": {},
                            "count": 0
                        },
                        "fraud": {
                            "text": {
                                "fraud": [
                                    {
                                        "0": "We and our partners use cookies and other tools for advertising, to help stop fraud, and for other purposes. By using this site, you agree to how your information is used as outlined in our Privacy Policy."
                                    },
                                    {
                                        "1": "Add extra protection to your account to help keep yourself safe from fraud and scams."
                                    },
                                    {
                                        "2": "Add extra protection to your account to help keep yourself safe from fraud and scams."
                                    },
                                    {
                                        "3": "Older adults in particular are at risk for fraud. Learn how you can help us protect your accounts."
                                    },
                                    {
                                        "4": "TIP: Chase will never ask you to send money back to yourself to reverse fraud on your account or to fix an issue."
                                    },
                                    {
                                        "5": "Think you may have experienced fraud? Here's what to do next."
                                    },
                                    {
                                        "6": "Learn safety practices and the steps you can take to help protect yourself from fraud and scams.\n"
                                    },
                                    {
                                        "7": "How to spot fraud and scams"
                                    },
                                    {
                                        "8": "Our suite of security features can help you protect your info, money and give you peace of mind. See how we're dedicated to helping protect you, your accounts and your loved ones from financial abuse. Also, learn about the common tricks scammers are using to help you stay one step ahead of them. If you see unauthorized charges or believe your account was compromised contact us right away to report fraud."
                                    }
                                ]
                            },
                            "count": 9
                        },
                        "to detect": {
                            "text": {},
                            "count": 0
                        },
                        "malicious": {
                            "text": {},
                            "count": 0
                        },
                        "illegal activity": {
                            "text": {},
                            "count": 0
                        },
                        "to protect": {
                            "text": {
                                "to protect": [
                                    {
                                        "0": ",   on what you can do to protect yourself"
                                    },
                                    {
                                        "1": ",   on what you can do to protect yourself"
                                    },
                                    {
                                        "2": "We're working to make your banking safer. See how we're helping to protect you and your accounts.\n"
                                    },
                                    {
                                        "3": ",   on how we work to protect you"
                                    },
                                    {
                                        "4": ",  on ways to protect yourself"
                                    }
                                ]
                            },
                            "count": 5
                        },
                        "encryption": {
                            "text": {},
                            "count": 0
                        },
                        "security": {
                            "text": {
                                "security": [
                                    {
                                        "0": "Welcome to the Chase Security Center"
                                    },
                                    {
                                        "1": "Our suite of security features can help protect your info and money, and give you peace of mind."
                                    },
                                    {
                                        "2": "Security Center home"
                                    },
                                    {
                                        "3": "Security Center home"
                                    },
                                    {
                                        "4": "Chase Security Center"
                                    },
                                    {
                                        "5": "suite of security features"
                                    }
                                ]
                            },
                            "count": 6
                        },
                        "unauthorized": {
                            "text": {
                                "unauthorized": [
                                    {
                                        "0": "You won't be held responsible for unauthorized charges made with your credit card. If you see an unauthorized charge, tell us immediately by calling the number on the back of your card or billing statement\n        \n        Footnote\n        2Opens overlay."
                                    },
                                    {
                                        "1": "If you see that money was removed from your checking or savings accounts through our mobile or online banking bill pay or transfer services and you didn’t authorize the transaction, let us know right away. We’ll reimburse you for those unauthorized transactions when you contact us promptly after the transaction first appears on your statement."
                                    },
                                    {
                                        "2": "Our suite of security features can help you protect your info, money and give you peace of mind. See how we're dedicated to helping protect you, your accounts and your loved ones from financial abuse. Also, learn about the common tricks scammers are using to help you stay one step ahead of them. If you see unauthorized charges or believe your account was compromised contact us right away to report fraud."
                                    }
                                ]
                            },
                            "count": 3
                        },
                        "auditing": {
                            "text": {},
                            "count": 0
                        }
                    },
                    "EDUCATION": {
                        "how": {
                            "text": {
                                "how": [
                                    {
                                        "0": "We and our partners use cookies and other tools for advertising, to help stop fraud, and for other purposes. By using this site, you agree to how your information is used as outlined in our Privacy Policy."
                                    },
                                    {
                                        "1": "How we protect you"
                                    },
                                    {
                                        "2": "How to use Zelle® safely"
                                    },
                                    {
                                        "3": "How we protect you"
                                    },
                                    {
                                        "4": "How to use Zelle® safely"
                                    },
                                    {
                                        "5": "How we protect you"
                                    },
                                    {
                                        "6": "We're continuously working to make your banking safer. See how we're dedicated to helping protect you and your accounts."
                                    },
                                    {
                                        "7": ",   on how Chase helps protect you"
                                    },
                                    {
                                        "8": "How we protect you"
                                    },
                                    {
                                        "9": "We're continuously working to make your banking safer. See how we're dedicated to helping protect you and your accounts."
                                    },
                                    {
                                        "10": ",   on how Chase helps protect you"
                                    },
                                    {
                                        "11": "Learn how to steer clear of scammers when using Zelle®"
                                    },
                                    {
                                        "12": "Older adults in particular are at risk for fraud. Learn how you can help us protect your accounts."
                                    },
                                    {
                                        "13": "Learn how to help take control of your future by recognizing the signs of financial abuse and exploitation. Get the tools to help you stay safe."
                                    },
                                    {
                                        "14": "We treat your personal and financial information with care. Our Privacy Policy explains how."
                                    },
                                    {
                                        "15": "How we help protect you"
                                    },
                                    {
                                        "16": "We're working to make your banking safer. See how we're helping to protect you and your accounts.\n"
                                    },
                                    {
                                        "17": ",   on how we work to protect you"
                                    },
                                    {
                                        "18": "How to spot fraud and scams"
                                    },
                                    {
                                        "19": ",   on how to spot scams"
                                    },
                                    {
                                        "20": "How do I know if an email received is a scam?"
                                    },
                                    {
                                        "21": "Our suite of security features can help you protect your info, money and give you peace of mind. See how we're dedicated to helping protect you, your accounts and your loved ones from financial abuse. Also, learn about the common tricks scammers are using to help you stay one step ahead of them. If you see unauthorized charges or believe your account was compromised contact us right away to report fraud."
                                    }
                                ]
                            },
                            "count": 22
                        },
                        "what": {
                            "text": {
                                "what": [
                                    {
                                        "0": "What you can do"
                                    },
                                    {
                                        "1": "What you can do"
                                    },
                                    {
                                        "2": "What you can do"
                                    },
                                    {
                                        "3": ",   on what you can do to protect yourself"
                                    },
                                    {
                                        "4": "What you can do"
                                    },
                                    {
                                        "5": ",   on what you can do to protect yourself"
                                    },
                                    {
                                        "6": "What to watch out for"
                                    },
                                    {
                                        "7": "Think you may have experienced fraud? Here's what to do next."
                                    },
                                    {
                                        "8": "What you can do to help protect yourself"
                                    },
                                    {
                                        "9": "Scammers spend their days coming up with new ways to trick us. Learn what to watch out for to help keep yourself safe.\n"
                                    },
                                    {
                                        "10": "What should I do if I suspect I've been targeted by a scammer?"
                                    },
                                    {
                                        "11": "Apply for a mortgage or refinance your mortgage with Chase. View today’s mortgage rates or calculate what you can afford with our mortgage calculator. Visit our Education Center for homebuying tips and more."
                                    }
                                ]
                            },
                            "count": 12
                        },
                        "how you": {
                            "text": {
                                "how you": [
                                    {
                                        "0": "Older adults in particular are at risk for fraud. Learn how you can help us protect your accounts."
                                    }
                                ]
                            },
                            "count": 1
                        },
                        "how we ": {
                            "text": {},
                            "count": 0
                        },
                        "explain": {
                            "text": {},
                            "count": 0
                        },
                        "understand": {
                            "text": {},
                            "count": 0
                        },
                        "learn": {
                            "text": {
                                "learn": [
                                    {
                                        "0": "Learn more"
                                    },
                                    {
                                        "1": "Learn more"
                                    },
                                    {
                                        "2": "Learn more"
                                    },
                                    {
                                        "3": "Learn more"
                                    },
                                    {
                                        "4": "Learn how to steer clear of scammers when using Zelle®"
                                    },
                                    {
                                        "5": "Older adults in particular are at risk for fraud. Learn how you can help us protect your accounts."
                                    },
                                    {
                                        "6": "Learn how to help take control of your future by recognizing the signs of financial abuse and exploitation. Get the tools to help you stay safe."
                                    },
                                    {
                                        "7": "Learn more about the common tricks scammers are using to help keep yourself safe."
                                    },
                                    {
                                        "8": "Learn more,   on how we work to protect you"
                                    },
                                    {
                                        "9": "Learn safety practices and the steps you can take to help protect yourself from fraud and scams.\n"
                                    },
                                    {
                                        "10": "Learn more,  on ways to protect yourself"
                                    },
                                    {
                                        "11": "Learn more,   about financial abuse"
                                    },
                                    {
                                        "12": "Scammers spend their days coming up with new ways to trick us. Learn what to watch out for to help keep yourself safe.\n"
                                    },
                                    {
                                        "13": "Learn more,   on how to spot scams"
                                    },
                                    {
                                        "14": "Many of us rely on technology to store and access financial information. Learn about the online do's and don'ts to help stay protected.\n"
                                    },
                                    {
                                        "15": "Learn more,   about online threats"
                                    },
                                    {
                                        "16": "learn about the common tricks scammers are using"
                                    },
                                    {
                                        "17": "Chase serves millions of people with a broad range of products. Chase online lets you manage your Chase accounts, view statements, monitor activity, pay bills or transfer funds securely from one central place. To learn more, visit the Banking Education Center. For questions or concerns, please contact Chase customer service or let us know about Chase complaints and feedback. View the Chase Community Reinvestment Act Public File for the bank’s latest CRA rating and other CRA-related information."
                                    },
                                    {
                                        "18": "Get more from a personalized relationship offering no everyday banking fees, priority service from a dedicated team and special perks and benefits. Connect with a Chase Private Client Banker at your nearest Chase branch to learn about eligibility requirements and all available benefits."
                                    }
                                ]
                            },
                            "count": 19
                        },
                        "more information": {
                            "text": {},
                            "count": 0
                        },
                        "educational resource": {
                            "text": {},
                            "count": 0
                        },
                        "educate": {
                            "text": {},
                            "count": 0
                        }
                    },
                    "TECHNOLOGY": {
                        "cookies": {
                            "text": {
                                "cookies": [
                                    {
                                        "0": "We and our partners use cookies and other tools for advertising, to help stop fraud, and for other purposes. By using this site, you agree to how your information is used as outlined in our Privacy Policy."
                                    }
                                ]
                            },
                            "count": 1
                        },
                        "mobile identifiers": {
                            "text": {},
                            "count": 0
                        },
                        "pixel tags": {
                            "text": {},
                            "count": 0
                        },
                        "web beacons": {
                            "text": {},
                            "count": 0
                        },
                        "session monitoring": {
                            "text": {},
                            "count": 0
                        }
                    }
                }
            }
        },
        "entry": 1
    }
}